immagent/__init__.py
immagent/advance.py
immagent/assets.py
immagent/exceptions.py
immagent/llm.py
immagent/logging.py
immagent/mcp.py
immagent/messages.py
immagent/persistent.py
immagent/py.typed
immagent/registry.py
immagent/simple.py
immagent/store.py
immagent-0.1.2.dist-info/WHEEL
immagent-0.1.2.dist-info/METADATA
immagent-0.1.2.dist-info/RECORD
