Metadata-Version: 2.4
Name: immagent
Version: 0.1.2
Summary: Immutable agent architecture with UUID-based identity
Keywords: ai,agents,llm,immutable,postgresql
Author: Kleanthes Koniaris
Author-email: Kleanthes Koniaris <kleanthes@gmail.com>
License-Expression: MIT
Classifier: Development Status :: 3 - Alpha
Classifier: Intended Audience :: Developers
Classifier: License :: OSI Approved :: MIT License
Classifier: Programming Language :: Python :: 3
Classifier: Programming Language :: Python :: 3.13
Classifier: Topic :: Scientific/Engineering :: Artificial Intelligence
Classifier: Typing :: Typed
Requires-Dist: litellm
Requires-Dist: asyncpg
Requires-Dist: mcp
Requires-Dist: pytest ; extra == 'dev'
Requires-Dist: pytest-asyncio ; extra == 'dev'
Requires-Dist: pytest-cov ; extra == 'dev'
Requires-Dist: ruff ; extra == 'dev'
Requires-Dist: testcontainers[postgres] ; extra == 'dev'
Requires-Python: >=3.13
Project-URL: Homepage, https://github.com/kgk/immagent-py
Project-URL: Issues, https://github.com/kgk/immagent-py/issues
Project-URL: Repository, https://github.com/kgk/immagent-py
Provides-Extra: dev
